slash_command_decorator/__init__.py
slash_command_decorator/event.py
slash_command_decorator/message.py
slash_command_decorator/reaction.py
slash_command_decorator/slash_command.py
slash_command_decorator-0.0.3.dist-info/DESCRIPTION.rst
slash_command_decorator-0.0.3.dist-info/METADATA
slash_command_decorator-0.0.3.dist-info/RECORD
slash_command_decorator-0.0.3.dist-info/WHEEL
slash_command_decorator-0.0.3.dist-info/metadata.json
slash_command_decorator-0.0.3.dist-info/top_level.txt
