Metadata-Version: 2.0
Name: slash-command-decorator
Version: 0.0.3
Summary: Useful Slack Slash Command decorators for AWS Lambda.
Home-page: https://github.com/penta515/slash-command-decorator
Author: penta515
Author-email: penta0515@gmail.com
License: UNKNOWN
Platform: UNKNOWN
Requires-Dist: slacker
